dtgn/__init__.py
dtgn/__main__.py
dtgn/args/Args.py
dtgn/args/__init__.py
dtgn/output/Output.py
dtgn/output/__init__.py
dtgn-1.0.2.dist-info/LICENSE.md
dtgn-1.0.2.dist-info/METADATA
dtgn-1.0.2.dist-info/WHEEL
dtgn-1.0.2.dist-info/entry_points.txt
dtgn-1.0.2.dist-info/top_level.txt
dtgn-1.0.2.dist-info/RECORD
