Metadata-Version: 2.1
Name: dtgn
Version: 1.0.2
Summary: Creates folder structures and puts data in it
Home-page: https://github.com/5f0ne/dtgn
Author: 5f0
License: MIT
Classifier: Operating System :: OS Independent 
Classifier: Programming Language :: Python :: 3 
Classifier: License :: OSI Approved :: MIT License 
License-File: LICENSE.md
